{"pageContext":{"jsonName":"en-page-2-065","internalComponentName":"ComponentEnPage2","path":"/en/page-2/","component":"/home/bszil/code/github/zyxneo/snow-white/src/pages/page-2.js","componentChunkName":"component---src-pages-page-2-js","context":{"languages":[{"value":"en","text":"English"},{"value":"hu","text":"Magyar"}],"locale":"en","routed":true,"originalPath":"/page-2/"},"updatedAt":1543947936548,"pluginCreator___NODE":"Plugin default-site-plugin","pluginCreatorId":"Plugin default-site-plugin","componentPath":"/home/bszil/code/github/zyxneo/snow-white/src/pages/page-2.js","languages":[{"value":"en","text":"English"},{"value":"hu","text":"Magyar"}],"locale":"en","routed":true,"originalPath":"/page-2/"}}